st_multi_icon_menu/__init__.py
st_multi_icon_menu/frontend/build/asset-manifest.json
st_multi_icon_menu/frontend/build/bootstrap.min.css
st_multi_icon_menu/frontend/build/index.html
st_multi_icon_menu/frontend/build/precache-manifest.fec58984c37b119fb32c6b714ad9909e.js
st_multi_icon_menu/frontend/build/service-worker.js
st_multi_icon_menu/frontend/build/static/js/2.9f86750f.chunk.js
st_multi_icon_menu/frontend/build/static/js/2.9f86750f.chunk.js.LICENSE.txt
st_multi_icon_menu/frontend/build/static/js/2.9f86750f.chunk.js.map
st_multi_icon_menu/frontend/build/static/js/main.5b5aca42.chunk.js
st_multi_icon_menu/frontend/build/static/js/main.5b5aca42.chunk.js.map
st_multi_icon_menu/frontend/build/static/js/runtime-main.8d5aa75d.js
st_multi_icon_menu/frontend/build/static/js/runtime-main.8d5aa75d.js.map
st_multi_icon_menu-0.1.3.dist-info/licenses/LICENSE
st_multi_icon_menu-0.1.3.dist-info/METADATA
st_multi_icon_menu-0.1.3.dist-info/WHEEL
st_multi_icon_menu-0.1.3.dist-info/top_level.txt
st_multi_icon_menu-0.1.3.dist-info/RECORD
