Metadata-Version: 2.4
Name: st_multi_icon_menu
Version: 0.1.3
Summary: Streamlit Component for ANT Menu with Bootstrap icon support
Home-page: https://github.com/locupleto/st_multi_icon_menu
Author: Urban Ottosson
Author-email: urban@ottosson.org
Requires-Python: >=3.6
License-File: LICENSE
Requires-Dist: streamlit>=0.63
Dynamic: author
Dynamic: author-email
Dynamic: description
Dynamic: description-content-type
Dynamic: home-page
Dynamic: license-file
Dynamic: requires-dist
Dynamic: requires-python
Dynamic: summary
